[{"id":7105,"article_id":6918,"ticker":"NFLX","sentiment_label":"neutral","sentiment_score":0.015071788802742958,"confidence":0.9364517331123352,"created_at":"2026-05-08T18:32:22+00:00"},{"id":7106,"article_id":6919,"ticker":"NFLX","sentiment_label":"neutral","sentiment_score":0.03179384768009186,"confidence":0.7436983585357666,"created_at":"2026-05-08T18:32:22+00:00"},{"id":7109,"article_id":6917,"ticker":"NFLX","sentiment_label":"negative","sentiment_score":-0.942349586635828,"confidence":0.9528611898422241,"created_at":"2026-05-08T18:32:22+00:00"},{"id":7113,"article_id":6916,"ticker":"NFLX","sentiment_label":"neutral","sentiment_score":0.26439260318875313,"confidence":0.7026968598365784,"created_at":"2026-05-08T18:32:22+00:00"},{"id":7115,"article_id":6915,"ticker":"NFLX","sentiment_label":"neutral","sentiment_score":0.3961893552914262,"confidence":0.5784696936607361,"created_at":"2026-05-08T18:32:22+00:00"},{"id":7117,"article_id":6914,"ticker":"NFLX","sentiment_label":"neutral","sentiment_score":0.0032580289989709854,"confidence":0.9427915811538696,"created_at":"2026-05-08T18:32:22+00:00"},{"id":7118,"article_id":6913,"ticker":"NFLX","sentiment_label":"positive","sentiment_score":0.6390862446278334,"confidence":0.6498429179191589,"created_at":"2026-05-08T18:32:22+00:00"},{"id":7129,"article_id":6912,"ticker":"NFLX","sentiment_label":"neutral","sentiment_score":-0.005739361047744751,"confidence":0.9057478308677673,"created_at":"2026-05-08T18:32:22+00:00"},{"id":7133,"article_id":6909,"ticker":"NFLX","sentiment_label":"neutral","sentiment_score":0.04785742424428463,"confidence":0.917574942111969,"created_at":"2026-05-08T18:32:22+00:00"},{"id":7134,"article_id":6910,"ticker":"NFLX","sentiment_label":"neutral","sentiment_score":-0.03961123898625374,"confidence":0.9052839279174805,"created_at":"2026-05-08T18:32:22+00:00"},{"id":7135,"article_id":6911,"ticker":"NFLX","sentiment_label":"neutral","sentiment_score":0.0537441149353981,"confidence":0.9124796390533447,"created_at":"2026-05-08T18:32:22+00:00"},{"id":7144,"article_id":6908,"ticker":"NFLX","sentiment_label":"neutral","sentiment_score":0.2217702753841877,"confidence":0.7110920548439026,"created_at":"2026-05-08T18:32:22+00:00"},{"id":7149,"article_id":6907,"ticker":"NFLX","sentiment_label":"positive","sentiment_score":0.4970512930303812,"confidence":0.5081982016563416,"created_at":"2026-05-08T18:32:22+00:00"},{"id":7153,"article_id":6906,"ticker":"NFLX","sentiment_label":"neutral","sentiment_score":0.014057783409953117,"confidence":0.9246253371238708,"created_at":"2026-05-08T18:32:22+00:00"},{"id":7157,"article_id":6905,"ticker":"NFLX","sentiment_label":"neutral","sentiment_score":0.016928095370531082,"confidence":0.9491496086120605,"created_at":"2026-05-08T18:32:22+00:00"},{"id":7190,"article_id":6904,"ticker":"NFLX","sentiment_label":"neutral","sentiment_score":0.024613624438643456,"confidence":0.9372642636299133,"created_at":"2026-05-08T18:32:22+00:00"},{"id":7213,"article_id":6903,"ticker":"NFLX","sentiment_label":"negative","sentiment_score":-0.9383716806769371,"confidence":0.9499313235282898,"created_at":"2026-05-08T18:32:22+00:00"},{"id":7221,"article_id":6901,"ticker":"NFLX","sentiment_label":"negative","sentiment_score":-0.9538202323019505,"confidence":0.9606166481971741,"created_at":"2026-05-08T18:32:22+00:00"},{"id":7222,"article_id":6902,"ticker":"NFLX","sentiment_label":"negative","sentiment_score":-0.6263891197741032,"confidence":0.6656572222709656,"created_at":"2026-05-08T18:32:22+00:00"},{"id":7234,"article_id":6900,"ticker":"NFLX","sentiment_label":"neutral","sentiment_score":-7.880665361881256e-05,"confidence":0.9465063214302063,"created_at":"2026-05-08T18:32:22+00:00"},{"id":6922,"article_id":6746,"ticker":"NFLX","sentiment_label":"neutral","sentiment_score":0.13486560806632042,"confidence":0.8369787931442261,"created_at":"2026-05-08T15:35:29+00:00"},{"id":6923,"article_id":6747,"ticker":"NFLX","sentiment_label":"positive","sentiment_score":0.907875794917345,"confidence":0.9229572415351868,"created_at":"2026-05-08T15:35:29+00:00"},{"id":6924,"article_id":6745,"ticker":"NFLX","sentiment_label":"neutral","sentiment_score":0.21216685511171818,"confidence":0.7552558183670044,"created_at":"2026-05-08T15:35:29+00:00"},{"id":6952,"article_id":6743,"ticker":"NFLX","sentiment_label":"neutral","sentiment_score":0.12189189158380032,"confidence":0.8389544486999512,"created_at":"2026-05-08T15:35:29+00:00"},{"id":6953,"article_id":6742,"ticker":"NFLX","sentiment_label":"neutral","sentiment_score":0.18620083201676607,"confidence":0.7835328578948975,"created_at":"2026-05-08T15:35:29+00:00"},{"id":6955,"article_id":6741,"ticker":"NFLX","sentiment_label":"neutral","sentiment_score":-0.003981281071901321,"confidence":0.9135050177574158,"created_at":"2026-05-08T15:35:29+00:00"},{"id":6958,"article_id":6740,"ticker":"NFLX","sentiment_label":"neutral","sentiment_score":0.3894603028893471,"confidence":0.5802885293960571,"created_at":"2026-05-08T15:35:29+00:00"},{"id":6967,"article_id":6739,"ticker":"NFLX","sentiment_label":"positive","sentiment_score":0.5638293381780386,"confidence":0.5845832824707031,"created_at":"2026-05-08T15:35:29+00:00"},{"id":6986,"article_id":6738,"ticker":"NFLX","sentiment_label":"neutral","sentiment_score":0.06376540847122669,"confidence":0.9116973280906677,"created_at":"2026-05-08T15:35:29+00:00"},{"id":6988,"article_id":6737,"ticker":"NFLX","sentiment_label":"neutral","sentiment_score":-0.03491185978055,"confidence":0.8718774914741516,"created_at":"2026-05-08T15:35:29+00:00"},{"id":6991,"article_id":6736,"ticker":"NFLX","sentiment_label":"positive","sentiment_score":0.5738475657999516,"confidence":0.5836640000343323,"created_at":"2026-05-08T15:35:29+00:00"},{"id":6993,"article_id":6663,"ticker":"NFLX","sentiment_label":"positive","sentiment_score":0.8455556659027934,"confidence":0.8607962131500244,"created_at":"2026-05-08T15:35:29+00:00"},{"id":6996,"article_id":6735,"ticker":"NFLX","sentiment_label":"positive","sentiment_score":0.8455556659027934,"confidence":0.8607962131500244,"created_at":"2026-05-08T15:35:29+00:00"},{"id":7003,"article_id":6734,"ticker":"NFLX","sentiment_label":"neutral","sentiment_score":-0.24006202071905136,"confidence":0.6438535451889038,"created_at":"2026-05-08T15:35:29+00:00"},{"id":7011,"article_id":6732,"ticker":"NFLX","sentiment_label":"neutral","sentiment_score":-0.3997846879065037,"confidence":0.5158025622367859,"created_at":"2026-05-08T15:35:29+00:00"},{"id":7012,"article_id":6733,"ticker":"NFLX","sentiment_label":"neutral","sentiment_score":-0.31516651809215546,"confidence":0.569560706615448,"created_at":"2026-05-08T15:35:29+00:00"},{"id":7037,"article_id":6731,"ticker":"NFLX","sentiment_label":"neutral","sentiment_score":0.09826508536934853,"confidence":0.8733862042427063,"created_at":"2026-05-08T15:35:29+00:00"},{"id":7040,"article_id":6730,"ticker":"NFLX","sentiment_label":"positive","sentiment_score":0.4107574224472046,"confidence":0.4712386131286621,"created_at":"2026-05-08T15:35:29+00:00"},{"id":7051,"article_id":6729,"ticker":"NFLX","sentiment_label":"neutral","sentiment_score":0.04350168630480766,"confidence":0.8996760249137878,"created_at":"2026-05-08T15:35:29+00:00"},{"id":6736,"article_id":6578,"ticker":"NFLX","sentiment_label":"neutral","sentiment_score":-0.005516264587640762,"confidence":0.9198024868965149,"created_at":"2026-05-08T12:31:20+00:00"},{"id":6753,"article_id":6576,"ticker":"NFLX","sentiment_label":"neutral","sentiment_score":0.015736185014247894,"confidence":0.925003707408905,"created_at":"2026-05-08T12:31:20+00:00"},{"id":6759,"article_id":6575,"ticker":"NFLX","sentiment_label":"neutral","sentiment_score":0.00356215238571167,"confidence":0.9321351051330566,"created_at":"2026-05-08T12:31:20+00:00"},{"id":6762,"article_id":6465,"ticker":"NFLX","sentiment_label":"neutral","sentiment_score":-0.22927959263324738,"confidence":0.4778864085674286,"created_at":"2026-05-08T12:31:20+00:00"},{"id":6764,"article_id":6515,"ticker":"NFLX","sentiment_label":"neutral","sentiment_score":-0.22927959263324738,"confidence":0.4778864085674286,"created_at":"2026-05-08T12:31:20+00:00"},{"id":6766,"article_id":6574,"ticker":"NFLX","sentiment_label":"neutral","sentiment_score":-0.22927959263324738,"confidence":0.4778864085674286,"created_at":"2026-05-08T12:31:20+00:00"},{"id":6785,"article_id":6571,"ticker":"NFLX","sentiment_label":"neutral","sentiment_score":0.2599425036460161,"confidence":0.7158492803573608,"created_at":"2026-05-08T12:31:20+00:00"},{"id":6786,"article_id":6572,"ticker":"NFLX","sentiment_label":"negative","sentiment_score":-0.7643072325736284,"confidence":0.7848802804946899,"created_at":"2026-05-08T12:31:20+00:00"},{"id":6787,"article_id":6573,"ticker":"NFLX","sentiment_label":"neutral","sentiment_score":0.07510829158127308,"confidence":0.887927234172821,"created_at":"2026-05-08T12:31:20+00:00"},{"id":6791,"article_id":6567,"ticker":"NFLX","sentiment_label":"neutral","sentiment_score":-0.3984352611005306,"confidence":0.5355916619300842,"created_at":"2026-05-08T12:31:20+00:00"},{"id":6792,"article_id":6568,"ticker":"NFLX","sentiment_label":"neutral","sentiment_score":0.06976553238928318,"confidence":0.8883671164512634,"created_at":"2026-05-08T12:31:20+00:00"},{"id":6793,"article_id":6569,"ticker":"NFLX","sentiment_label":"neutral","sentiment_score":0.09390971250832081,"confidence":0.8719919323921204,"created_at":"2026-05-08T12:31:20+00:00"},{"id":6794,"article_id":6570,"ticker":"NFLX","sentiment_label":"neutral","sentiment_score":0.1485702581703663,"confidence":0.8055194020271301,"created_at":"2026-05-08T12:31:20+00:00"},{"id":6795,"article_id":6566,"ticker":"NFLX","sentiment_label":"neutral","sentiment_score":0.11235443875193596,"confidence":0.8584050536155701,"created_at":"2026-05-08T12:31:20+00:00"},{"id":6797,"article_id":6565,"ticker":"NFLX","sentiment_label":"neutral","sentiment_score":0.06736372597515583,"confidence":0.8779469728469849,"created_at":"2026-05-08T12:31:20+00:00"},{"id":6798,"article_id":6564,"ticker":"NFLX","sentiment_label":"neutral","sentiment_score":0.009034214541316032,"confidence":0.936734139919281,"created_at":"2026-05-08T12:31:20+00:00"},{"id":6804,"article_id":6562,"ticker":"NFLX","sentiment_label":"neutral","sentiment_score":-0.15892170369625092,"confidence":0.7651572823524475,"created_at":"2026-05-08T12:31:20+00:00"},{"id":6805,"article_id":6563,"ticker":"NFLX","sentiment_label":"neutral","sentiment_score":0.09350168891251087,"confidence":0.8722648620605469,"created_at":"2026-05-08T12:31:20+00:00"},{"id":6816,"article_id":6561,"ticker":"NFLX","sentiment_label":"neutral","sentiment_score":0.13368286937475204,"confidence":0.8248597383499146,"created_at":"2026-05-08T12:31:20+00:00"},{"id":6820,"article_id":6560,"ticker":"NFLX","sentiment_label":"neutral","sentiment_score":0.2040654942393303,"confidence":0.7242234945297241,"created_at":"2026-05-08T12:31:20+00:00"},{"id":6835,"article_id":6559,"ticker":"NFLX","sentiment_label":"neutral","sentiment_score":0.08490173704922199,"confidence":0.8889687657356262,"created_at":"2026-05-08T12:31:20+00:00"},{"id":6582,"article_id":6416,"ticker":"NFLX","sentiment_label":"neutral","sentiment_score":0.15232775919139385,"confidence":0.8141943216323853,"created_at":"2026-05-08T09:35:19+00:00"},{"id":6583,"article_id":6415,"ticker":"NFLX","sentiment_label":"negative","sentiment_score":-0.7178904917091131,"confidence":0.7330422401428223,"created_at":"2026-05-08T09:35:19+00:00"},{"id":6585,"article_id":6414,"ticker":"NFLX","sentiment_label":"neutral","sentiment_score":0.11479087360203266,"confidence":0.8258774280548096,"created_at":"2026-05-08T09:35:19+00:00"},{"id":6587,"article_id":6413,"ticker":"NFLX","sentiment_label":"positive","sentiment_score":0.11632180213928223,"confidence":0.5310571789741516,"created_at":"2026-05-08T09:35:19+00:00"},{"id":6589,"article_id":6412,"ticker":"NFLX","sentiment_label":"positive","sentiment_score":0.8186458498239517,"confidence":0.827458918094635,"created_at":"2026-05-08T09:35:19+00:00"},{"id":6591,"article_id":6411,"ticker":"NFLX","sentiment_label":"neutral","sentiment_score":0.19307364709675312,"confidence":0.7509504556655884,"created_at":"2026-05-08T09:35:19+00:00"},{"id":6598,"article_id":6410,"ticker":"NFLX","sentiment_label":"neutral","sentiment_score":0.01943110302090645,"confidence":0.8769189715385437,"created_at":"2026-05-08T09:35:19+00:00"},{"id":6599,"article_id":6409,"ticker":"NFLX","sentiment_label":"neutral","sentiment_score":0.0022532716393470764,"confidence":0.9368306398391724,"created_at":"2026-05-08T09:35:19+00:00"},{"id":6605,"article_id":6408,"ticker":"NFLX","sentiment_label":"positive","sentiment_score":0.65638492628932,"confidence":0.6738821864128113,"created_at":"2026-05-08T09:35:19+00:00"},{"id":6616,"article_id":6407,"ticker":"NFLX","sentiment_label":"neutral","sentiment_score":0.03503719996660948,"confidence":0.9342049956321716,"created_at":"2026-05-08T09:35:19+00:00"},{"id":6621,"article_id":6406,"ticker":"NFLX","sentiment_label":"neutral","sentiment_score":0.10092948377132416,"confidence":0.8642511963844299,"created_at":"2026-05-08T09:35:19+00:00"},{"id":6627,"article_id":6405,"ticker":"NFLX","sentiment_label":"neutral","sentiment_score":-0.01523548737168312,"confidence":0.8869017958641052,"created_at":"2026-05-08T09:35:19+00:00"},{"id":6630,"article_id":6404,"ticker":"NFLX","sentiment_label":"neutral","sentiment_score":0.1309039443731308,"confidence":0.8486257791519165,"created_at":"2026-05-08T09:35:19+00:00"},{"id":6631,"article_id":6403,"ticker":"NFLX","sentiment_label":"negative","sentiment_score":-0.8943845480680466,"confidence":0.9295894503593445,"created_at":"2026-05-08T09:35:19+00:00"},{"id":6655,"article_id":6400,"ticker":"NFLX","sentiment_label":"negative","sentiment_score":-0.7973860967904329,"confidence":0.8164304494857788,"created_at":"2026-05-08T09:35:19+00:00"},{"id":6678,"article_id":6399,"ticker":"NFLX","sentiment_label":"neutral","sentiment_score":0.12573657650500536,"confidence":0.8490009307861328,"created_at":"2026-05-08T09:35:19+00:00"},{"id":6429,"article_id":6283,"ticker":"NFLX","sentiment_label":"negative","sentiment_score":-0.9548931894823909,"confidence":0.962931752204895,"created_at":"2026-05-08T06:39:09+00:00"},{"id":6431,"article_id":6282,"ticker":"NFLX","sentiment_label":"neutral","sentiment_score":0.014734048396348953,"confidence":0.9127795100212097,"created_at":"2026-05-08T06:39:09+00:00"},{"id":6434,"article_id":6281,"ticker":"NFLX","sentiment_label":"neutral","sentiment_score":0.10235870815813541,"confidence":0.8642629384994507,"created_at":"2026-05-08T06:39:09+00:00"},{"id":6436,"article_id":6280,"ticker":"NFLX","sentiment_label":"neutral","sentiment_score":0.0005043409764766693,"confidence":0.9364105463027954,"created_at":"2026-05-08T06:39:09+00:00"},{"id":6444,"article_id":6277,"ticker":"NFLX","sentiment_label":"neutral","sentiment_score":0.047756003215909004,"confidence":0.8985833525657654,"created_at":"2026-05-08T06:39:09+00:00"},{"id":6445,"article_id":6278,"ticker":"NFLX","sentiment_label":"neutral","sentiment_score":0.10823174752295017,"confidence":0.8725070953369141,"created_at":"2026-05-08T06:39:09+00:00"},{"id":6446,"article_id":6279,"ticker":"NFLX","sentiment_label":"neutral","sentiment_score":-0.013386830687522888,"confidence":0.9138181805610657,"created_at":"2026-05-08T06:39:09+00:00"},{"id":6448,"article_id":6276,"ticker":"NFLX","sentiment_label":"neutral","sentiment_score":0.03659123741090298,"confidence":0.9204055070877075,"created_at":"2026-05-08T06:39:09+00:00"},{"id":6453,"article_id":6275,"ticker":"NFLX","sentiment_label":"neutral","sentiment_score":-0.033995360136032104,"confidence":0.7924392223358154,"created_at":"2026-05-08T06:39:09+00:00"},{"id":6478,"article_id":6274,"ticker":"NFLX","sentiment_label":"neutral","sentiment_score":0.0904965028166771,"confidence":0.8325009346008301,"created_at":"2026-05-08T06:39:09+00:00"},{"id":6510,"article_id":6273,"ticker":"NFLX","sentiment_label":"neutral","sentiment_score":0.3109827423468232,"confidence":0.6706067323684692,"created_at":"2026-05-08T06:39:09+00:00"},{"id":6512,"article_id":6272,"ticker":"NFLX","sentiment_label":"neutral","sentiment_score":-0.14487725496292114,"confidence":0.7627611756324768,"created_at":"2026-05-08T06:39:09+00:00"},{"id":6513,"article_id":6271,"ticker":"NFLX","sentiment_label":"neutral","sentiment_score":0.0820322036743164,"confidence":0.883220374584198,"created_at":"2026-05-08T06:39:09+00:00"},{"id":6522,"article_id":6270,"ticker":"NFLX","sentiment_label":"positive","sentiment_score":0.9383656792342663,"confidence":0.9588792324066162,"created_at":"2026-05-08T06:39:09+00:00"},{"id":6525,"article_id":6269,"ticker":"NFLX","sentiment_label":"neutral","sentiment_score":0.09984694980084896,"confidence":0.8516404032707214,"created_at":"2026-05-08T06:39:09+00:00"},{"id":6568,"article_id":6268,"ticker":"NFLX","sentiment_label":"neutral","sentiment_score":0.004864618182182312,"confidence":0.944533109664917,"created_at":"2026-05-08T06:39:09+00:00"},{"id":6290,"article_id":6152,"ticker":"NFLX","sentiment_label":"negative","sentiment_score":-0.8367880349978805,"confidence":0.852126955986023,"created_at":"2026-05-08T04:06:48+00:00"},{"id":6298,"article_id":6150,"ticker":"NFLX","sentiment_label":"negative","sentiment_score":-0.5788627695292234,"confidence":0.6053927540779114,"created_at":"2026-05-08T04:06:48+00:00"},{"id":6304,"article_id":6149,"ticker":"NFLX","sentiment_label":"negative","sentiment_score":-0.926238764077425,"confidence":0.9382320642471313,"created_at":"2026-05-08T04:06:48+00:00"},{"id":6305,"article_id":6148,"ticker":"NFLX","sentiment_label":"neutral","sentiment_score":0.18473602458834648,"confidence":0.7928977608680725,"created_at":"2026-05-08T04:06:48+00:00"},{"id":6308,"article_id":6147,"ticker":"NFLX","sentiment_label":"neutral","sentiment_score":0.062054092064499855,"confidence":0.8963207006454468,"created_at":"2026-05-08T04:06:48+00:00"},{"id":6311,"article_id":6146,"ticker":"NFLX","sentiment_label":"neutral","sentiment_score":-0.09682622179389,"confidence":0.817700207233429,"created_at":"2026-05-08T04:06:48+00:00"},{"id":6316,"article_id":6145,"ticker":"NFLX","sentiment_label":"negative","sentiment_score":-0.9509678734466434,"confidence":0.9601424336433411,"created_at":"2026-05-08T04:06:48+00:00"},{"id":6318,"article_id":6143,"ticker":"NFLX","sentiment_label":"neutral","sentiment_score":0.0798798929899931,"confidence":0.8856068253517151,"created_at":"2026-05-08T04:06:48+00:00"},{"id":6319,"article_id":6144,"ticker":"NFLX","sentiment_label":"negative","sentiment_score":-0.9320201082155108,"confidence":0.9435878992080688,"created_at":"2026-05-08T04:06:48+00:00"},{"id":6335,"article_id":6142,"ticker":"NFLX","sentiment_label":"neutral","sentiment_score":0.099562156945467,"confidence":0.8656681776046753,"created_at":"2026-05-08T04:06:48+00:00"},{"id":6378,"article_id":6028,"ticker":"NFLX","sentiment_label":"neutral","sentiment_score":0.046666473150253296,"confidence":0.8990525603294373,"created_at":"2026-05-08T04:06:48+00:00"},{"id":6379,"article_id":6141,"ticker":"NFLX","sentiment_label":"neutral","sentiment_score":0.046666473150253296,"confidence":0.8990525603294373,"created_at":"2026-05-08T04:06:48+00:00"},{"id":6393,"article_id":6140,"ticker":"NFLX","sentiment_label":"neutral","sentiment_score":0.055529993027448654,"confidence":0.9070205092430115,"created_at":"2026-05-08T04:06:48+00:00"},{"id":6422,"article_id":6139,"ticker":"NFLX","sentiment_label":"negative","sentiment_score":-0.5952168349176645,"confidence":0.6211301684379578,"created_at":"2026-05-08T04:06:48+00:00"},{"id":6129,"article_id":6015,"ticker":"NFLX","sentiment_label":"neutral","sentiment_score":0.03876087628304958,"confidence":0.9070239067077637,"created_at":"2026-05-08T00:37:34+00:00"},{"id":6130,"article_id":6014,"ticker":"NFLX","sentiment_label":"negative","sentiment_score":-0.8634064849466085,"confidence":0.8806749582290649,"created_at":"2026-05-08T00:37:34+00:00"},{"id":6131,"article_id":6013,"ticker":"NFLX","sentiment_label":"negative","sentiment_score":-0.748210646212101,"confidence":0.7682788372039795,"created_at":"2026-05-08T00:37:34+00:00"},{"id":6132,"article_id":6011,"ticker":"NFLX","sentiment_label":"neutral","sentiment_score":-0.05247151665389538,"confidence":0.9010080099105835,"created_at":"2026-05-08T00:37:34+00:00"},{"id":6133,"article_id":6012,"ticker":"NFLX","sentiment_label":"neutral","sentiment_score":-0.09501786530017853,"confidence":0.8235471248626709,"created_at":"2026-05-08T00:37:34+00:00"},{"id":6134,"article_id":6010,"ticker":"NFLX","sentiment_label":"neutral","sentiment_score":0.04208455979824066,"confidence":0.8999314308166504,"created_at":"2026-05-08T00:37:34+00:00"},{"id":6137,"article_id":6009,"ticker":"NFLX","sentiment_label":"neutral","sentiment_score":-0.012522667646408081,"confidence":0.9097929000854492,"created_at":"2026-05-08T00:37:34+00:00"},{"id":6142,"article_id":6008,"ticker":"NFLX","sentiment_label":"negative","sentiment_score":-0.7305763494223356,"confidence":0.7507433891296387,"created_at":"2026-05-08T00:37:34+00:00"},{"id":6143,"article_id":6007,"ticker":"NFLX","sentiment_label":"negative","sentiment_score":-0.46606187149882317,"confidence":0.4974045753479004,"created_at":"2026-05-08T00:37:34+00:00"},{"id":6179,"article_id":6006,"ticker":"NFLX","sentiment_label":"neutral","sentiment_score":-0.05429923161864281,"confidence":0.8753087520599365,"created_at":"2026-05-08T00:37:34+00:00"},{"id":6193,"article_id":6005,"ticker":"NFLX","sentiment_label":"neutral","sentiment_score":0.03399627283215523,"confidence":0.894102931022644,"created_at":"2026-05-08T00:37:34+00:00"},{"id":6212,"article_id":5865,"ticker":"NFLX","sentiment_label":"neutral","sentiment_score":0.1878410167992115,"confidence":0.7709949016571045,"created_at":"2026-05-08T00:37:34+00:00"},{"id":6214,"article_id":6004,"ticker":"NFLX","sentiment_label":"neutral","sentiment_score":0.1878410167992115,"confidence":0.7709949016571045,"created_at":"2026-05-08T00:37:34+00:00"},{"id":6217,"article_id":6003,"ticker":"NFLX","sentiment_label":"negative","sentiment_score":-0.6017713155597448,"confidence":0.63173907995224,"created_at":"2026-05-08T00:37:34+00:00"},{"id":6224,"article_id":6002,"ticker":"NFLX","sentiment_label":"neutral","sentiment_score":0.003074139356613159,"confidence":0.9286263585090637,"created_at":"2026-05-08T00:37:34+00:00"},{"id":6235,"article_id":6001,"ticker":"NFLX","sentiment_label":"negative","sentiment_score":-0.31606025993824005,"confidence":0.470271497964859,"created_at":"2026-05-08T00:37:34+00:00"},{"id":6241,"article_id":6000,"ticker":"NFLX","sentiment_label":"neutral","sentiment_score":-0.3820471651852131,"confidence":0.5410423278808594,"created_at":"2026-05-08T00:37:34+00:00"},{"id":6250,"article_id":5999,"ticker":"NFLX","sentiment_label":"neutral","sentiment_score":0.008362457156181335,"confidence":0.8075234293937683,"created_at":"2026-05-08T00:37:34+00:00"},{"id":6254,"article_id":5998,"ticker":"NFLX","sentiment_label":"neutral","sentiment_score":0.010782063007354736,"confidence":0.9159939885139465,"created_at":"2026-05-08T00:37:34+00:00"},{"id":6266,"article_id":5997,"ticker":"NFLX","sentiment_label":"positive","sentiment_score":0.9071071296930313,"confidence":0.93602454662323,"created_at":"2026-05-08T00:37:34+00:00"},{"id":6277,"article_id":5996,"ticker":"NFLX","sentiment_label":"neutral","sentiment_score":0.16449637338519096,"confidence":0.7991040945053101,"created_at":"2026-05-08T00:37:34+00:00"},{"id":5990,"article_id":5855,"ticker":"NFLX","sentiment_label":"positive","sentiment_score":0.41897210478782654,"confidence":0.7005815505981445,"created_at":"2026-05-07T21:23:31+00:00"},{"id":5991,"article_id":5853,"ticker":"NFLX","sentiment_label":"positive","sentiment_score":0.753049686551094,"confidence":0.8658419251441956,"created_at":"2026-05-07T21:23:31+00:00"},{"id":5992,"article_id":5854,"ticker":"NFLX","sentiment_label":"positive","sentiment_score":0.753049686551094,"confidence":0.8658419251441956,"created_at":"2026-05-07T21:23:31+00:00"},{"id":5997,"article_id":5852,"ticker":"NFLX","sentiment_label":"negative","sentiment_score":-0.9636797411367297,"confidence":0.9716536998748779,"created_at":"2026-05-07T21:23:31+00:00"},{"id":6004,"article_id":5851,"ticker":"NFLX","sentiment_label":"negative","sentiment_score":-0.9194708047434688,"confidence":0.9276005625724792,"created_at":"2026-05-07T21:23:31+00:00"},{"id":6008,"article_id":5850,"ticker":"NFLX","sentiment_label":"negative","sentiment_score":-0.9375230129808187,"confidence":0.9486437439918518,"created_at":"2026-05-07T21:23:31+00:00"},{"id":6014,"article_id":5849,"ticker":"NFLX","sentiment_label":"neutral","sentiment_score":-0.042565036565065384,"confidence":0.8860222697257996,"created_at":"2026-05-07T21:23:31+00:00"},{"id":6015,"article_id":5848,"ticker":"NFLX","sentiment_label":"neutral","sentiment_score":-0.029126744717359543,"confidence":0.8509217500686646,"created_at":"2026-05-07T21:23:31+00:00"},{"id":6016,"article_id":5847,"ticker":"NFLX","sentiment_label":"neutral","sentiment_score":0.02391503006219864,"confidence":0.9287441968917847,"created_at":"2026-05-07T21:23:31+00:00"},{"id":6020,"article_id":5846,"ticker":"NFLX","sentiment_label":"neutral","sentiment_score":0.026534361764788628,"confidence":0.9293164610862732,"created_at":"2026-05-07T21:23:31+00:00"},{"id":6023,"article_id":5845,"ticker":"NFLX","sentiment_label":"neutral","sentiment_score":0.010248832404613495,"confidence":0.9158870577812195,"created_at":"2026-05-07T21:23:31+00:00"},{"id":6024,"article_id":5844,"ticker":"NFLX","sentiment_label":"neutral","sentiment_score":-0.05295615829527378,"confidence":0.8936166167259216,"created_at":"2026-05-07T21:23:31+00:00"},{"id":6025,"article_id":5843,"ticker":"NFLX","sentiment_label":"neutral","sentiment_score":0.03759938105940819,"confidence":0.8888161778450012,"created_at":"2026-05-07T21:23:31+00:00"},{"id":6031,"article_id":5842,"ticker":"NFLX","sentiment_label":"neutral","sentiment_score":0.03436637669801712,"confidence":0.8901068568229675,"created_at":"2026-05-07T21:23:31+00:00"},{"id":6066,"article_id":5841,"ticker":"NFLX","sentiment_label":"neutral","sentiment_score":0.1287214607000351,"confidence":0.8015121221542358,"created_at":"2026-05-07T21:23:31+00:00"},{"id":6069,"article_id":5840,"ticker":"NFLX","sentiment_label":"neutral","sentiment_score":-0.12911526300013065,"confidence":0.8156569004058838,"created_at":"2026-05-07T21:23:31+00:00"},{"id":6074,"article_id":5839,"ticker":"NFLX","sentiment_label":"neutral","sentiment_score":-0.12549728155136108,"confidence":0.7312330603599548,"created_at":"2026-05-07T21:23:31+00:00"},{"id":6084,"article_id":5838,"ticker":"NFLX","sentiment_label":"negative","sentiment_score":-0.8504006080329418,"confidence":0.8670582175254822,"created_at":"2026-05-07T21:23:31+00:00"},{"id":6094,"article_id":5837,"ticker":"NFLX","sentiment_label":"neutral","sentiment_score":-0.06960752233862877,"confidence":0.8255668878555298,"created_at":"2026-05-07T21:23:31+00:00"},{"id":5798,"article_id":5695,"ticker":"NFLX","sentiment_label":"neutral","sentiment_score":-0.22838770225644112,"confidence":0.6800437569618225,"created_at":"2026-05-07T18:36:54+00:00"},{"id":5802,"article_id":5694,"ticker":"NFLX","sentiment_label":"neutral","sentiment_score":0.04566100984811783,"confidence":0.8812795281410217,"created_at":"2026-05-07T18:36:54+00:00"},{"id":5809,"article_id":5693,"ticker":"NFLX","sentiment_label":"neutral","sentiment_score":0.03320665657520294,"confidence":0.900723934173584,"created_at":"2026-05-07T18:36:54+00:00"},{"id":5813,"article_id":5692,"ticker":"NFLX","sentiment_label":"positive","sentiment_score":0.4184872433543205,"confidence":0.48173418641090393,"created_at":"2026-05-07T18:36:54+00:00"},{"id":5820,"article_id":5691,"ticker":"NFLX","sentiment_label":"neutral","sentiment_score":0.07234951760619879,"confidence":0.8978672027587891,"created_at":"2026-05-07T18:36:54+00:00"},{"id":5822,"article_id":5690,"ticker":"NFLX","sentiment_label":"neutral","sentiment_score":0.03918938525021076,"confidence":0.9292540550231934,"created_at":"2026-05-07T18:36:54+00:00"},{"id":5841,"article_id":5688,"ticker":"NFLX","sentiment_label":"neutral","sentiment_score":0.004306036978960037,"confidence":0.8927354216575623,"created_at":"2026-05-07T18:36:54+00:00"},{"id":5845,"article_id":5687,"ticker":"NFLX","sentiment_label":"neutral","sentiment_score":0.15029539912939072,"confidence":0.8157528638839722,"created_at":"2026-05-07T18:36:54+00:00"},{"id":5847,"article_id":5686,"ticker":"NFLX","sentiment_label":"neutral","sentiment_score":-0.3797380533069372,"confidence":0.5733686685562134,"created_at":"2026-05-07T18:36:54+00:00"},{"id":5848,"article_id":5685,"ticker":"NFLX","sentiment_label":"neutral","sentiment_score":0.02260627970099449,"confidence":0.9424802660942078,"created_at":"2026-05-07T18:36:54+00:00"},{"id":5852,"article_id":5684,"ticker":"NFLX","sentiment_label":"neutral","sentiment_score":0.029847338795661926,"confidence":0.9201013445854187,"created_at":"2026-05-07T18:36:54+00:00"},{"id":5855,"article_id":5683,"ticker":"NFLX","sentiment_label":"neutral","sentiment_score":-0.15162768214941025,"confidence":0.7573906779289246,"created_at":"2026-05-07T18:36:54+00:00"},{"id":5858,"article_id":5682,"ticker":"NFLX","sentiment_label":"neutral","sentiment_score":0.10999481938779354,"confidence":0.8505483269691467,"created_at":"2026-05-07T18:36:54+00:00"},{"id":5869,"article_id":5681,"ticker":"NFLX","sentiment_label":"neutral","sentiment_score":-0.01760859228670597,"confidence":0.9221007823944092,"created_at":"2026-05-07T18:36:54+00:00"},{"id":5872,"article_id":5680,"ticker":"NFLX","sentiment_label":"neutral","sentiment_score":-0.05219511687755585,"confidence":0.8928148746490479,"created_at":"2026-05-07T18:36:54+00:00"},{"id":5899,"article_id":5679,"ticker":"NFLX","sentiment_label":"neutral","sentiment_score":-0.03499535843729973,"confidence":0.9018052816390991,"created_at":"2026-05-07T18:36:54+00:00"},{"id":5906,"article_id":5678,"ticker":"NFLX","sentiment_label":"neutral","sentiment_score":0.054782792925834656,"confidence":0.9189773201942444,"created_at":"2026-05-07T18:36:54+00:00"},{"id":5928,"article_id":5677,"ticker":"NFLX","sentiment_label":"negative","sentiment_score":-0.8265378437936306,"confidence":0.8614169359207153,"created_at":"2026-05-07T18:36:54+00:00"},{"id":5935,"article_id":5524,"ticker":"NFLX","sentiment_label":"neutral","sentiment_score":0.034822722896933556,"confidence":0.9176846742630005,"created_at":"2026-05-07T18:36:54+00:00"},{"id":5936,"article_id":5676,"ticker":"NFLX","sentiment_label":"neutral","sentiment_score":0.034822722896933556,"confidence":0.9176846742630005,"created_at":"2026-05-07T18:36:54+00:00"},{"id":5619,"article_id":5521,"ticker":"NFLX","sentiment_label":"neutral","sentiment_score":0.1267204750329256,"confidence":0.8465575575828552,"created_at":"2026-05-07T15:48:46+00:00"},{"id":5627,"article_id":5520,"ticker":"NFLX","sentiment_label":"neutral","sentiment_score":0.08184880390763283,"confidence":0.8700656890869141,"created_at":"2026-05-07T15:48:46+00:00"},{"id":5628,"article_id":5519,"ticker":"NFLX","sentiment_label":"neutral","sentiment_score":0.0867860522121191,"confidence":0.8597299456596375,"created_at":"2026-05-07T15:48:46+00:00"},{"id":5641,"article_id":5513,"ticker":"NFLX","sentiment_label":"neutral","sentiment_score":-0.019195888191461563,"confidence":0.8793171048164368,"created_at":"2026-05-07T15:48:46+00:00"},{"id":5642,"article_id":5514,"ticker":"NFLX","sentiment_label":"neutral","sentiment_score":0.0021901801228523254,"confidence":0.9254873394966125,"created_at":"2026-05-07T15:48:46+00:00"},{"id":5643,"article_id":5515,"ticker":"NFLX","sentiment_label":"neutral","sentiment_score":0.18952347431331873,"confidence":0.7851641178131104,"created_at":"2026-05-07T15:48:46+00:00"},{"id":5644,"article_id":5516,"ticker":"NFLX","sentiment_label":"neutral","sentiment_score":0.009050387889146805,"confidence":0.9132264852523804,"created_at":"2026-05-07T15:48:46+00:00"},{"id":5645,"article_id":5517,"ticker":"NFLX","sentiment_label":"neutral","sentiment_score":0.010616255924105644,"confidence":0.9338149428367615,"created_at":"2026-05-07T15:48:46+00:00"},{"id":5646,"article_id":5518,"ticker":"NFLX","sentiment_label":"neutral","sentiment_score":0.09246616065502167,"confidence":0.8817028403282166,"created_at":"2026-05-07T15:48:46+00:00"},{"id":5652,"article_id":5512,"ticker":"NFLX","sentiment_label":"neutral","sentiment_score":0.06763823516666889,"confidence":0.8983049392700195,"created_at":"2026-05-07T15:48:46+00:00"},{"id":5656,"article_id":5511,"ticker":"NFLX","sentiment_label":"neutral","sentiment_score":0.0660605002194643,"confidence":0.8992162942886353,"created_at":"2026-05-07T15:48:46+00:00"},{"id":5659,"article_id":5510,"ticker":"NFLX","sentiment_label":"neutral","sentiment_score":-0.002971641719341278,"confidence":0.9099298715591431,"created_at":"2026-05-07T15:48:46+00:00"},{"id":5662,"article_id":5509,"ticker":"NFLX","sentiment_label":"neutral","sentiment_score":0.01327970065176487,"confidence":0.9474167823791504,"created_at":"2026-05-07T15:48:46+00:00"},{"id":5685,"article_id":5508,"ticker":"NFLX","sentiment_label":"neutral","sentiment_score":-0.07627498731017113,"confidence":0.8584128022193909,"created_at":"2026-05-07T15:48:46+00:00"},{"id":5702,"article_id":5507,"ticker":"NFLX","sentiment_label":"neutral","sentiment_score":-0.017984433099627495,"confidence":0.9195879101753235,"created_at":"2026-05-07T15:48:46+00:00"},{"id":5708,"article_id":5506,"ticker":"NFLX","sentiment_label":"neutral","sentiment_score":0.05194006487727165,"confidence":0.9003843069076538,"created_at":"2026-05-07T15:48:46+00:00"},{"id":5709,"article_id":5505,"ticker":"NFLX","sentiment_label":"neutral","sentiment_score":0.03628459759056568,"confidence":0.9099245667457581,"created_at":"2026-05-07T15:48:46+00:00"},{"id":5750,"article_id":5504,"ticker":"NFLX","sentiment_label":"neutral","sentiment_score":-0.2003119457513094,"confidence":0.7586538791656494,"created_at":"2026-05-07T15:48:46+00:00"},{"id":5751,"article_id":5503,"ticker":"NFLX","sentiment_label":"neutral","sentiment_score":0.4823713656514883,"confidence":0.4997427463531494,"created_at":"2026-05-07T15:48:46+00:00"},{"id":5757,"article_id":5502,"ticker":"NFLX","sentiment_label":"neutral","sentiment_score":0.4222326036542654,"confidence":0.5590274333953857,"created_at":"2026-05-07T15:48:46+00:00"},{"id":5438,"article_id":5349,"ticker":"NFLX","sentiment_label":"neutral","sentiment_score":0.04174998961389065,"confidence":0.9101932048797607,"created_at":"2026-05-07T12:40:21+00:00"},{"id":5443,"article_id":5348,"ticker":"NFLX","sentiment_label":"neutral","sentiment_score":0.12060617096722126,"confidence":0.8414932489395142,"created_at":"2026-05-07T12:40:21+00:00"},{"id":5453,"article_id":5347,"ticker":"NFLX","sentiment_label":"neutral","sentiment_score":0.22484620474278927,"confidence":0.7333990335464478,"created_at":"2026-05-07T12:40:21+00:00"},{"id":5454,"article_id":5346,"ticker":"NFLX","sentiment_label":"neutral","sentiment_score":-0.21978042274713516,"confidence":0.6647364497184753,"created_at":"2026-05-07T12:40:21+00:00"},{"id":5455,"article_id":5345,"ticker":"NFLX","sentiment_label":"neutral","sentiment_score":0.021886304020881653,"confidence":0.9145486354827881,"created_at":"2026-05-07T12:40:21+00:00"},{"id":5460,"article_id":5344,"ticker":"NFLX","sentiment_label":"neutral","sentiment_score":0.009490877389907837,"confidence":0.915780782699585,"created_at":"2026-05-07T12:40:21+00:00"},{"id":5464,"article_id":5341,"ticker":"NFLX","sentiment_label":"neutral","sentiment_score":0.22106131818145514,"confidence":0.757495641708374,"created_at":"2026-05-07T12:40:21+00:00"},{"id":5465,"article_id":5342,"ticker":"NFLX","sentiment_label":"neutral","sentiment_score":0.0013701729476451874,"confidence":0.9248901009559631,"created_at":"2026-05-07T12:40:21+00:00"},{"id":5469,"article_id":5340,"ticker":"NFLX","sentiment_label":"neutral","sentiment_score":0.02949872985482216,"confidence":0.9280942678451538,"created_at":"2026-05-07T12:40:21+00:00"},{"id":5482,"article_id":5338,"ticker":"NFLX","sentiment_label":"neutral","sentiment_score":0.031023068353533745,"confidence":0.9330978989601135,"created_at":"2026-05-07T12:40:21+00:00"},{"id":5483,"article_id":5339,"ticker":"NFLX","sentiment_label":"neutral","sentiment_score":0.032480720430612564,"confidence":0.8874789476394653,"created_at":"2026-05-07T12:40:21+00:00"},{"id":5489,"article_id":5337,"ticker":"NFLX","sentiment_label":"neutral","sentiment_score":0.17241051979362965,"confidence":0.78935706615448,"created_at":"2026-05-07T12:40:21+00:00"},{"id":5491,"article_id":5336,"ticker":"NFLX","sentiment_label":"neutral","sentiment_score":-0.008652672171592712,"confidence":0.9083352088928223,"created_at":"2026-05-07T12:40:21+00:00"},{"id":5519,"article_id":5334,"ticker":"NFLX","sentiment_label":"neutral","sentiment_score":0.2154777403920889,"confidence":0.7624518871307373,"created_at":"2026-05-07T12:40:21+00:00"}]